dir2path/__init__.py
dir2path/console.py
dir2path-0.1.0.dist-info/entry_points.txt
dir2path-0.1.0.dist-info/LICENSE
dir2path-0.1.0.dist-info/WHEEL
dir2path-0.1.0.dist-info/METADATA
dir2path-0.1.0.dist-info/RECORD
