Metadata-Version: 2.1
Name: dir2path
Version: 0.1.0
Summary: Add current directory to your PATH
Author: Josh Burns
Author-email: joshyburnss@gmail.com
Requires-Python: >=3.11,<4.0
Classifier: Programming Language :: Python :: 3
Classifier: Programming Language :: Python :: 3.11
